pynter/__init__.py
pynter/config_default.yml
pynter/automations/__init__.py
pynter/automations/core.py
pynter/automations/vasp.py
pynter/cli/analysis.py
pynter/cli/automations.py
pynter/cli/config.py
pynter/cli/defects.py
pynter/cli/hpc.py
pynter/cli/inputs.py
pynter/cli/main.py
pynter/cli/materials_project.py
pynter/cli/phase_diagram.py
pynter/cli/plotter.py
pynter/cli/slurm.py
pynter/cli/utils.py
pynter/data/__init__.py
pynter/data/datasets.py
pynter/data/jobs.py
pynter/data/database/__init__.py
pynter/data/database/creator.py
pynter/data/database/query.py
pynter/defects/__init__.py
pynter/defects/analysis.py
pynter/defects/corrections.py
pynter/defects/defects.py
pynter/defects/elasticity.py
pynter/defects/entries.py
pynter/defects/plotter.py
pynter/defects/structure.py
pynter/defects/thermodynamics.py
pynter/defects/utils.py
pynter/defects/pmg/pmg_defects_core.py
pynter/defects/pmg/pmg_defects_corrections.py
pynter/defects/pmg/pmg_defects_utils.py
pynter/defects/pmg/pmg_dos.py
pynter/phase_diagram/__init__.py
pynter/phase_diagram/chempots.py
pynter/phase_diagram/plotter.py
pynter/phase_diagram/thermodynamics.py
pynter/slurm/__init__.py
pynter/slurm/core.py
pynter/slurm/interface.py
pynter/slurm/job_settings.py
pynter/slurm/job_status.py
pynter/slurm/slurm_arguments.txt
pynter/slurm/slurm_arguments_help.txt
pynter/testing/__init__.py
pynter/testing/core.py
pynter/testing/data.py
pynter/testing/defects.py
pynter/testing/phase_diagram.py
pynter/testing/slurm.py
pynter/testing/structure.py
pynter/testing/vasp.py
pynter/tools/__init__.py
pynter/tools/format.py
pynter/tools/materials_project.py
pynter/tools/plotter.py
pynter/tools/structure.py
pynter/tools/utils.py
pynter/vasp/__init__.py
pynter/vasp/analysis.py
pynter/vasp/default_inputs.py
pynter/vasp/jobs.py
pynter/vasp/plotter.py
pynter/vasp/schemes.py
pynter/vasp/utils.py
pynter/vasp/vasp_default.yml
pynter/vasp/pmg/pmg_electronic_structure_dos.py
pynter/vasp/pmg/pmg_electronic_structure_plotter.py
pynter_defects-1.3.14.dist-info/METADATA
pynter_defects-1.3.14.dist-info/WHEEL
pynter_defects-1.3.14.dist-info/entry_points.txt
pynter_defects-1.3.14.dist-info/top_level.txt
pynter_defects-1.3.14.dist-info/RECORD
