Metadata-Version: 2.4
Name: pynter-defects
Version: 1.3.14
Summary: Tools for atomistic calculations, provides features for point-defect calculations
Author: Lorenzo Villa
Requires-Dist: ase
Requires-Dist: pymatgen>=2023.3.23
Requires-Dist: pymatgen-analysis-defects>=2023.3.25
Requires-Dist: pymatgen-db
Requires-Dist: PyYAML
Requires-Dist: schedule
Dynamic: author
Dynamic: description
Dynamic: description-content-type
Dynamic: requires-dist
Dynamic: summary
